setup.py
sdictviewer/__init__.py
sdictviewer/appstate.py
sdictviewer/articleformat.py
sdictviewer/dictinfo.py
sdictviewer/dictutil.py
sdictviewer/hildonui.py
sdictviewer/pyuca.py
sdictviewer/ui.py
sdictviewer.egg-info/PKG-INFO
sdictviewer.egg-info/SOURCES.txt
sdictviewer.egg-info/dependency_links.txt
sdictviewer.egg-info/entry_points.txt
sdictviewer.egg-info/top_level.txt
sdictviewer/formats/__init__.py
sdictviewer/formats/dct/__init__.py
sdictviewer/formats/dct/sdict.py
sdictviewer/formats/pdi/__init__.py
sdictviewer/formats/pdi/pdi.py