Metadata-Version: 1.0
Name: sdictviewer
Version: 0.6.2
Summary: SDict Viewer is a viewer for dictionaries in Sdictionary format.
Home-page: http://sdictviewer.sourceforge.net
Author: Igor Tkach
Author-email: itkach@gmail.com
License: GPL 3
Keywords: sdictviewer,dict,dictionary,maemo
Platform: UNKNOWN
Classifier: Development Status :: 5 - Production/Stable
Classifier: Operating System :: OS Independent
Classifier: Programming Language :: Python
Classifier: License :: OSI Approved :: GNU General Public License (GPL)
Classifier: Topic :: Utilities
Classifier: Environment :: X11 Applications :: GTK
